[
  {
    "title": "Still in Skyrim - 15th Anniversary",
    "description": "A consistent, stable modlist created to celebrate Skyrim\u2019s 15th anniversary, designed to stay artistically true to vanilla while refining the experience: enhancing what already works, smoothing out what does not, and preserving the unmistakable feel of Skyrim through carefully curated mods.",
    "author": "erdtreefaithful",
    "maintainers": [
      "github/erdtreefaithful"
    ],
    "game": "skyrimspecialedition",
    "official": false,
    "tags": [
      "Vanilla\u002B",
      "SFW",
      "Steam",
      "DLC Required"
    ],
    "nsfw": false,
    "utility_list": false,
    "image_contains_title": false,
    "DisplayVersionOnlyInInstallerView": false,
    "force_down": false,
    "links": {
      "image": "https://raw.githubusercontent.com/erdtreefaithful/stillinskyrim/main/assets/mainlogo-wj.webp",
      "readme": "https://www.nexusmods.com/skyrimspecialedition/mods/171497?tab=description",
      "download": "https://authored-files.wabbajack.org/StillinSkyrim15thAnniversaryRevision14.wabbajack_6c541e0a-9bb7-450d-b464-10ecad935101",
      "machineURL": "StillInSkyrim",
      "discordURL": "https://www.nexusmods.com/skyrimspecialedition/mods/171497?tab=posts",
      "websiteURL": "",
      "nexusCollection": {
        "collectionId": "434233",
        "slug": "litaki",
        "domainName": "skyrimspecialedition",
        "lastRevisionNumber": 14
      }
    },
    "download_metadata": {
      "Hash": "3xMag1bV8fA=",
      "Size": 12066242,
      "NumberOfArchives": 736,
      "SizeOfArchives": 88686761594,
      "NumberOfInstalledFiles": 42457,
      "SizeOfInstalledFiles": 99936835881,
      "TotalSize": 188623597475
    },
    "version": "14.0",
    "dateCreated": "1970-01-01T00:00:00Z",
    "dateUpdated": "2026-05-02T20:01:12.1792996Z",
    "repositoryName": ""
  }
]